{"cameraMode":{"drawMode":0,"name":"Shaded","section":"Shading Mode"},"sceneLighting":true,"audioPlay":false,"sceneViewState":{"m_AlwaysRefresh":false,"showFog":true,"showSkybox":true,"showFlares":true,"showImageEffects":true,"showParticleSystems":true,"showVisualEffectGraphs":true,"m_FxEnabled":true},"in2DMode":false,"pivot":{"x":-7.433233737945557,"y":4.137747764587402,"z":9.23055362701416},"rotation":{"x":-0.5684484839439392,"y":-0.37263503670692446,"z":0.3210712969303131,"w":-0.6595556735992432},"size":5.477250576019287,"orthographic":false}